arisdev/__init__.py
arisdev/api.py
arisdev/auth.py
arisdev/background.py
arisdev/cache.py
arisdev/database.py
arisdev/form.py
arisdev/framework.py
arisdev/logger.py
arisdev/middleware.py
arisdev/request.py
arisdev/response.py
arisdev/serializers.py
arisdev/tasks.py
arisdev/template.py
arisdev/upload.py
arisdev/validators.py
arisdev/websocket.py
arisdev-0.1.0.dist-info/LICENSE
arisdev-0.1.0.dist-info/METADATA
arisdev-0.1.0.dist-info/WHEEL
arisdev-0.1.0.dist-info/top_level.txt
arisdev-0.1.0.dist-info/RECORD
