Metadata-Version: 2.1
Name: arisdev
Version: 0.1.0
Summary: A simple web framework for Python
Home-page: https://github.com/arisdev/arisdev
Author: ArisDev
Author-email: arisdev@example.com
Classifier: Development Status :: 3 - Alpha
Classifier: Intended Audience :: Developers
Classifier: Topic :: Software Development :: Libraries :: Python Modules
Classifier: Programming Language :: Python :: 3
Classifier: Programming Language :: Python :: 3.6
Classifier: Programming Language :: Python :: 3.7
Classifier: Programming Language :: Python :: 3.8
Classifier: Programming Language :: Python :: 3.9
Classifier: Programming Language :: Python :: 3.10
Classifier: License :: OSI Approved :: MIT License
Classifier: Operating System :: OS Independent
Requires-Python: >=3.6
License-File: LICENSE
Requires-Dist: werkzeug>=2.0.0
Requires-Dist: jinja2>=3.0.0
Requires-Dist: sqlalchemy>=1.4.0
Requires-Dist: redis>=4.0.0
Requires-Dist: bcrypt>=3.2.0
Requires-Dist: pyjwt>=2.0.0
Requires-Dist: schedule>=1.1.0
Requires-Dist: websockets>=10.0.0
Provides-Extra: dev
Requires-Dist: pytest>=6.0.0; extra == "dev"
Requires-Dist: pytest-cov>=2.0.0; extra == "dev"
Requires-Dist: black>=21.0.0; extra == "dev"
Requires-Dist: isort>=5.0.0; extra == "dev"
Requires-Dist: flake8>=3.9.0; extra == "dev"
Requires-Dist: mypy>=0.910; extra == "dev"
